notebookize.py
notebookize-0.1.3.dist-info/licenses/LICENSE
notebookize-0.1.3.dist-info/WHEEL
notebookize-0.1.3.dist-info/METADATA
notebookize-0.1.3.dist-info/RECORD
